{
  "id": "https://www.opinion.com.bo/articulo/economia/bolivia-busca-regular-comercio-electronico/20231005120000898765.html",
  "title": "Bolivia busca regular el comercio electrónico con nueva ley",
  "summary": "El gobierno boliviano propone una legislación para regular las transacciones en línea, con el objetivo de proteger a consumidores y fomentar el comercio digital.",
  "url": "https://www.opinion.com.bo/articulo/economia/bolivia-busca-regular-comercio-electronico/20231005120000898765.html",
  "source": "Opinión",
  "source_url": "https://www.opinion.com.bo",
  "country": "Bolivia",
  "topics": [
    "Regulación",
    "Tecnología"
  ],
  "language": "es",
  "published_at": "2023-10-05T15:15:00Z",
  "relevance": 6,
  "sentiment": "neutral",
  "author": "Juan Morales",
  "curator": "Luciano AI",
  "generated_at": "2025-09-14T16:13:23.555Z",
  "date": "2025-09-13"
}