{
  "id": "https://www.lanacion.com.ar/politica/argentina-proyecto-ley-regular-plataformas-digitales-nid05102023/",
  "title": "Argentina impulsa proyecto de ley para regular plataformas digitales",
  "summary": "El gobierno argentino presentó un proyecto de ley que busca regular el funcionamiento de plataformas digitales y redes sociales, con énfasis en la protección de datos y la lucha contra la desinformación.",
  "url": "https://www.lanacion.com.ar/politica/argentina-proyecto-ley-regular-plataformas-digitales-nid05102023/",
  "source": "La Nación",
  "source_url": "https://www.lanacion.com.ar",
  "country": "Argentina",
  "topics": [
    "Regulación",
    "Tecnología",
    "Datos"
  ],
  "language": "es",
  "published_at": "2023-10-05T18:20:00Z",
  "relevance": 8,
  "sentiment": "neutral",
  "author": "Sofía Martínez",
  "curator": "Luciano AI",
  "generated_at": "2025-09-14T12:01:09.171Z",
  "date": "2025-09-14"
}